[{
  "_id": {
    "$oid": "6698e597f13ebc07eb0db034"
  },
  "ids": "pac-231",
  "date": {
    "$date": "2024-07-19T11:51:00.000Z"
  },
  "part": "ablaktörlő",
  "cost": 2000
},
{
  "_id": {
    "$oid": "669b7a3258280d985406b519"
  },
  "ids": "svf-719",
  "date": {
    "$date": "2024-07-25T10:49:00.000Z"
  },
  "part": "fékbetét 4 db",
  "cost": 30000
},
{
  "_id": {
    "$oid": "669d3ef2aaef807019010eb5"
  },
  "ids": "1",
  "date": {
    "$date": "2024-07-26T19:01:00.000Z"
  },
  "part": "ttttt",
  "cost": 1110
}]